[
  {
    "title": "Golang 第一课 安装与简介",
    "modifiedAt": "2021年03月25日",
    "image": "//cdn.global.eachin-life.com/image/85d365cf94395444b7f321eaa85e481c.jpeg",
    "link": "/article/3"
  },
  {
    "title": "浅谈测试开发的必要性",
    "modifiedAt": "2021年03月25日",
    "image": "//cdn.global.eachin-life.com/image/85d365cf94395444b7f321eaa85e481c.jpeg",
    "link": "/article/2"
  },
  {
    "title": "什么是CDN?",
    "modifiedAt": "2021年03月25日",
    "image": "//cdn.global.eachin-life.com/image/ac35b8e1613ca3da8328a068cfb023bf.jpeg",
    "link": "/article/1"
  }
]
